{
  "id": "83pyn8oq52a",
  "name": "Avalanche",
  "division": "8",
  "backgroundImage": "",
  "cards": [
    {
      "name": "Medusa",
      "imageUrl": "/uploads/cards/Medusa.webp",
      "type": "Crew",
      "subtype": "Driver",
      "buildPointCost": 0,
      "crewPointCost": 3,
      "numberAllowed": 1,
      "source": "Crew",
      "copies": 1,
      "exclusive": false,
      "sides": "",
      "id": "ed1de209-ae8c-4362-a44f-11135a5c9bb7-1751211061092-ycivwbm",
      "area": "crew",
      "x": 0,
      "y": 0
    },
    {
      "name": "Wheel Hubs",
      "imageUrl": "/uploads/cards/Wheel_Hubs.webp",
      "type": "Upgrade",
      "subtype": "",
      "buildPointCost": 2,
      "crewPointCost": 0,
      "numberAllowed": 1,
      "source": "Miniatures Set 1",
      "copies": 1,
      "exclusive": false,
      "sides": "",
      "id": "6bb383d3-9da5-4a20-8fe4-5300bcdd8b83-1751211190638-ff6qedc",
      "area": "gearupgrade",
      "x": 0,
      "y": 0
    },
    {
      "name": "Roll Bar",
      "imageUrl": "/uploads/cards/Roll_Bar.webp",
      "type": "Upgrade",
      "subtype": "Frame",
      "buildPointCost": 1,
      "crewPointCost": 0,
      "numberAllowed": 1,
      "source": "Miniatures Set 2",
      "copies": 1,
      "exclusive": false,
      "sides": "",
      "id": "76ac5e26-67e7-4770-a968-e489e46fc511-1751211199952-ztq505r",
      "area": "gearupgrade",
      "x": 0,
      "y": 0
    },
    {
      "name": "Hyperion",
      "imageUrl": "/uploads/cards/Hyperion.webp",
      "type": "Crew",
      "subtype": "Gunner",
      "buildPointCost": 0,
      "crewPointCost": 5,
      "numberAllowed": 1,
      "source": "Crew",
      "copies": 1,
      "exclusive": false,
      "sides": "",
      "id": "428acfec-9166-4800-834c-83591710d146-1751211270925-mib7p1c",
      "area": "crew",
      "x": 0,
      "y": 0
    },
    {
      "name": "Hand Cannon",
      "imageUrl": "/uploads/cards/Hand_Cannon.webp",
      "type": "Sidearm",
      "subtype": "",
      "buildPointCost": 0,
      "crewPointCost": 0,
      "numberAllowed": 1,
      "source": "Core",
      "copies": 1,
      "exclusive": false,
      "sides": "",
      "id": "71a4737c-76d2-4b0d-87f9-8c2431562e2e-1751211274300-egalz1h",
      "area": "crew",
      "x": 0,
      "y": 0
    },
    {
      "name": "Linked Jackhammers",
      "imageUrl": "/uploads/cards/Linked_Jackhammers.webp",
      "type": "Weapon",
      "subtype": "Slug",
      "buildPointCost": 6,
      "crewPointCost": 0,
      "numberAllowed": 2,
      "source": "Linked Weapons",
      "copies": 1,
      "exclusive": false,
      "sides": "fb",
      "id": "ad0ae633-65a1-4703-804d-88a4b0a87c61-1751211311123-fqye2em",
      "area": "front",
      "x": 0,
      "y": 0
    },
    {
      "name": "Linked Jackhammers",
      "imageUrl": "/uploads/cards/Linked_Jackhammers.webp",
      "type": "Weapon",
      "subtype": "Slug",
      "buildPointCost": 6,
      "crewPointCost": 0,
      "numberAllowed": 2,
      "source": "Linked Weapons",
      "copies": 1,
      "exclusive": false,
      "sides": "fb",
      "id": "ad0ae633-65a1-4703-804d-88a4b0a87c61-1751211314079-u5cf1y0",
      "area": "back",
      "x": 0,
      "y": 0
    },
    {
      "name": "Heavy Machine Gun",
      "imageUrl": "/uploads/cards/Heavy_Machine_Gun.webp",
      "type": "Weapon",
      "subtype": "Shred",
      "buildPointCost": 3,
      "crewPointCost": 0,
      "numberAllowed": 2,
      "source": "Core",
      "copies": 1,
      "exclusive": false,
      "sides": "",
      "id": "55c97349-598c-4b2a-8890-741f63d63e1e-1751211325531-pql1mjt",
      "area": "left",
      "x": 0,
      "y": 0
    },
    {
      "name": "Heavy Machine Gun",
      "imageUrl": "/uploads/cards/Heavy_Machine_Gun.webp",
      "type": "Weapon",
      "subtype": "Shred",
      "buildPointCost": 3,
      "crewPointCost": 0,
      "numberAllowed": 2,
      "source": "Core",
      "copies": 1,
      "exclusive": false,
      "sides": "",
      "id": "55c97349-598c-4b2a-8890-741f63d63e1e-1751211327720-gadlc7t",
      "area": "right",
      "x": 0,
      "y": 0
    },
    {
      "name": "Magnetic Dampers",
      "imageUrl": "/uploads/cards/Magnetic_Dampers.webp",
      "type": "Accessory",
      "subtype": "",
      "buildPointCost": 1,
      "crewPointCost": 0,
      "numberAllowed": 1,
      "source": "Miniatures Set 4",
      "copies": 1,
      "exclusive": false,
      "sides": "",
      "id": "a424ed8d-3e69-4dec-b874-bffdcb19143a-1751211337675-ko2yihc",
      "area": "back",
      "x": 0,
      "y": 0
    },
    {
      "name": "Heavy Ceramic Plate",
      "imageUrl": "/uploads/cards/Heavy_Ceramic_Plate.webp",
      "type": "Structure",
      "subtype": "",
      "buildPointCost": 3,
      "crewPointCost": 0,
      "numberAllowed": 4,
      "source": "Miniatures Set 1",
      "copies": 1,
      "exclusive": false,
      "sides": "",
      "id": "c331da7f-4823-4d97-a7e7-5a216dbccc0c-1751211374416-wr6k92f",
      "area": "front",
      "x": 0,
      "y": 0
    },
    {
      "name": "Heavy Ceramic Plate",
      "imageUrl": "/uploads/cards/Heavy_Ceramic_Plate.webp",
      "type": "Structure",
      "subtype": "",
      "buildPointCost": 3,
      "crewPointCost": 0,
      "numberAllowed": 4,
      "source": "Miniatures Set 1",
      "copies": 1,
      "exclusive": false,
      "sides": "",
      "id": "c331da7f-4823-4d97-a7e7-5a216dbccc0c-1751211375067-dlhobni",
      "area": "back",
      "x": 0,
      "y": 0
    },
    {
      "name": "Standard Ceramic Plate",
      "imageUrl": "/uploads/cards/Standard_Ceramic_Plate.webp",
      "type": "Structure",
      "subtype": "",
      "buildPointCost": 2,
      "crewPointCost": 0,
      "numberAllowed": 4,
      "source": "Miniatures Set 2",
      "copies": 1,
      "exclusive": false,
      "sides": "",
      "id": "3df1dce3-cd27-4ee7-a319-ed041e1b8d1d-1751211383251-u3wiugi",
      "area": "left",
      "x": 0,
      "y": 0
    },
    {
      "name": "Standard Ceramic Plate",
      "imageUrl": "/uploads/cards/Standard_Ceramic_Plate.webp",
      "type": "Structure",
      "subtype": "",
      "buildPointCost": 2,
      "crewPointCost": 0,
      "numberAllowed": 4,
      "source": "Miniatures Set 2",
      "copies": 1,
      "exclusive": false,
      "sides": "",
      "id": "3df1dce3-cd27-4ee7-a319-ed041e1b8d1d-1751211384055-f8mxj1z",
      "area": "right",
      "x": 0,
      "y": 0
    }
  ],
  "pointLimits": {
    "buildPoints": 32,
    "crewPoints": 8
  },
  "pointsUsed": {
    "buildPoints": 32,
    "crewPoints": 8
  }
}